MANIFEST.in
requirements.txt
setup.py
fever_api.egg-info/PKG-INFO
fever_api.egg-info/SOURCES.txt
fever_api.egg-info/dependency_links.txt
fever_api.egg-info/requires.txt
fever_api.egg-info/top_level.txt
src/fever/__init__.py
src/fever/api/__init__.py
src/fever/api/web_server.py