Metadata-Version: 1.2
Name: fever-api
Version: 1.0.25
Summary: Fact Extraction and VERification API
Home-page: https://jamesthorne.co.uk
Author: James Thorne
Author-email: james@jamesthorne.co.uk
License: Copyright 2019 James Thorne
